typf-0.1.0.dist-info/METADATA
typf-0.1.0.dist-info/WHEEL
typf/__init__.py
typf/typf.cpython-312-darwin.so
typf-0.1.0.dist-info/RECORD
