Metadata-Version: 2.4
Name: typf
Version: 0.1.0
Classifier: Development Status :: 3 - Alpha
Classifier: Intended Audience :: Developers
Classifier: License :: OSI Approved :: MIT License
Classifier: License :: OSI Approved :: Apache Software License
Classifier: Operating System :: MacOS
Classifier: Operating System :: Microsoft :: Windows
Classifier: Operating System :: POSIX :: Linux
Classifier: Programming Language :: Python :: 3
Classifier: Programming Language :: Python :: 3.8
Classifier: Programming Language :: Python :: 3.9
Classifier: Programming Language :: Python :: 3.10
Classifier: Programming Language :: Python :: 3.11
Classifier: Programming Language :: Python :: 3.12
Classifier: Programming Language :: Rust
Classifier: Topic :: Text Processing :: Fonts
Classifier: Topic :: Multimedia :: Graphics
Requires-Dist: pytest>=7.0 ; extra == 'dev'
Requires-Dist: pytest-benchmark ; extra == 'dev'
Requires-Dist: pillow ; extra == 'dev'
Requires-Dist: numpy ; extra == 'dev'
Requires-Dist: black ; extra == 'dev'
Requires-Dist: mypy ; extra == 'dev'
Provides-Extra: mac
Provides-Extra: windows
Provides-Extra: icu
Provides-Extra: skia
Provides-Extra: all
Provides-Extra: dev
Summary: High-performance, multi-backend text rendering for Python and Rust
Author-email: Font Laboratory <team@fontlab.org>
License: MIT OR Apache-2.0
Requires-Python: >=3.8
Project-URL: Homepage, https://github.com/fontlaborg/typf
Project-URL: Repository, https://github.com/fontlaborg/typf
Project-URL: Issues, https://github.com/fontlaborg/typf/issues
